paid/__init__.py
paid/agents/__init__.py
paid/agents/client.py
paid/agents/raw_client.py
paid/client.py
paid/contacts/__init__.py
paid/contacts/client.py
paid/contacts/raw_client.py
paid/core/__init__.py
paid/core/api_error.py
paid/core/client_wrapper.py
paid/core/datetime_utils.py
paid/core/file.py
paid/core/force_multipart.py
paid/core/http_client.py
paid/core/http_response.py
paid/core/jsonable_encoder.py
paid/core/pydantic_utilities.py
paid/core/query_encoder.py
paid/core/remove_none_from_dict.py
paid/core/request_options.py
paid/core/serialization.py
paid/customers/__init__.py
paid/customers/client.py
paid/customers/raw_client.py
paid/environment.py
paid/errors/__init__.py
paid/errors/bad_request_error.py
paid/errors/forbidden_error.py
paid/errors/internal_server_error.py
paid/errors/not_found_error.py
paid/logger.py
paid/orders/__init__.py
paid/orders/client.py
paid/orders/lines/__init__.py
paid/orders/lines/client.py
paid/orders/lines/raw_client.py
paid/orders/raw_client.py
paid/plans/__init__.py
paid/plans/client.py
paid/plans/raw_client.py
paid/products/__init__.py
paid/products/client.py
paid/products/raw_client.py
paid/products/types/__init__.py
paid/products/types/product_create_type.py
paid/py.typed
paid/traces/__init__.py
paid/traces/client.py
paid/traces/raw_client.py
paid/tracing/__init__.py
paid/tracing/autoinstrumentation.py
paid/tracing/context_data.py
paid/tracing/context_manager.py
paid/tracing/distributed_tracing.py
paid/tracing/signal.py
paid/tracing/tracing.py
paid/tracing/wrappers/__init__.py
paid/tracing/wrappers/anthropic/__init__.py
paid/tracing/wrappers/anthropic/anthropicWrapper.py
paid/tracing/wrappers/bedrock/__init__.py
paid/tracing/wrappers/bedrock/bedrockWrapper.py
paid/tracing/wrappers/gemini/__init__.py
paid/tracing/wrappers/gemini/geminiWrapper.py
paid/tracing/wrappers/langchain/__init__.py
paid/tracing/wrappers/langchain/paidLangChainCallback.py
paid/tracing/wrappers/llamaindex/__init__.py
paid_python-0.6.0.dist-info/LICENSE
paid_python-0.6.0.dist-info/METADATA
paid_python-0.6.0.dist-info/WHEEL
paid_python-0.6.0.dist-info/RECORD
