Metadata-Version: 2.1
Name: paid-python
Version: 0.6.0
Summary: 
Requires-Python: >=3.9,<3.14
Classifier: Intended Audience :: Developers
Classifier: Operating System :: MacOS
Classifier: Operating System :: Microsoft :: Windows
Classifier: Operating System :: OS Independent
Classifier: Operating System :: POSIX
Classifier: Operating System :: POSIX :: Linux
Classifier: Programming Language :: Python
Classifier: Programming Language :: Python :: 3
Classifier: Programming Language :: Python :: 3.9
Classifier: Programming Language :: Python :: 3.10
Classifier: Programming Language :: Python :: 3.11
Classifier: Programming Language :: Python :: 3.12
Classifier: Topic :: Software Development :: Libraries :: Python Modules
Classifier: Typing :: Typed
Requires-Dist: httpx (>=0.21.0)
Requires-Dist: mutagen (>=1.47.0)
Requires-Dist: openinference-instrumentation-bedrock (>=0.1.0)
Requires-Dist: openinference-instrumentation-google-genai (>=0.1.8)
Requires-Dist: openinference-instrumentation-langchain (>=0.1.55)
Requires-Dist: openinference-instrumentation-openai-agents (>=1.0.0)
Requires-Dist: opentelemetry-api (>=1.23.0)
Requires-Dist: opentelemetry-exporter-otlp-proto-http (>=1.23.0)
Requires-Dist: opentelemetry-instrumentation-anthropic (>=0.47.0)
Requires-Dist: opentelemetry-sdk (>=1.23.0)
Requires-Dist: pydantic (>=1.9.0)
Requires-Dist: pydantic-core (>=2.18.0)
Requires-Dist: python-dotenv (>=0.15.0)
Requires-Dist: typing_extensions (>=4.0.0)
